basic_pkg/.version
basic_pkg/__init__.py
basic_pkg/__main__.py
basic_pkg/sample_mod.py
basic_pkg/examples/Untitled.ipynb
basic_pkg/examples/example_doc.txt
mijn_pkg-0.0.8.dist-info/METADATA
mijn_pkg-0.0.8.dist-info/WHEEL
mijn_pkg-0.0.8.dist-info/entry_points.txt
mijn_pkg-0.0.8.dist-info/top_level.txt
mijn_pkg-0.0.8.dist-info/RECORD
